maxdmg_docgen/Docgen.py
maxdmg_docgen/__init__.py
maxdmg_docgen-0.0.3.dist-info/METADATA
maxdmg_docgen-0.0.3.dist-info/WHEEL
maxdmg_docgen-0.0.3.dist-info/top_level.txt
maxdmg_docgen-0.0.3.dist-info/RECORD
