Metadata-Version: 2.1
Name: maxdmg-docgen
Version: 0.0.3
Summary: This is a generator of docuemnts for maxdmg project.
Author: tonotonokon
Classifier: Programming Language :: Python :: 3
Classifier: License :: OSI Approved :: MIT License
Classifier: Operating System :: OS Independent
Requires-Python: >=3.10
Requires-Dist: docxtpl (==0.16.5)
